{
  "version": 3,
  "middleware": {
    "/": {
      "files": [
        "prerender-manifest.js",
        "server/edge-runtime-webpack.js",
        "server/middleware.js"
      ],
      "name": "middleware",
      "page": "/",
      "matchers": [
        {
          "regexp": "^(?:\\/(_next\\/data\\/[^/]{1,}))?\\/dashboard(?:\\/((?:[^\\/#\\?]+?)(?:\\/(?:[^\\/#\\?]+?))*))?(.json)?[\\/#\\?]?$",
          "originalSource": "/dashboard/:path*"
        },
        {
          "regexp": "^(?:\\/(_next\\/data\\/[^/]{1,}))?\\/auth(?:\\/((?:[^\\/#\\?]+?)(?:\\/(?:[^\\/#\\?]+?))*))?(.json)?[\\/#\\?]?$",
          "originalSource": "/auth/:path*"
        },
        {
          "regexp": "^(?:\\/(_next\\/data\\/[^/]{1,}))?\\/auth(.json)?[\\/#\\?]?$",
          "originalSource": "/auth"
        }
      ],
      "wasm": [],
      "assets": [],
      "environments": {
        "previewModeId": "905a8cbca3ae22f0b18ad7d9781422c4",
        "previewModeSigningKey": "8fde728fa08c681fe4cda1466bb1f2a9f0281f136936b0f64ca9c8b3d90c7a8b",
        "previewModeEncryptionKey": "caabb7dcc2a841711b5297bf563f2545fc99e357791240059dfe9f9384150747"
      }
    }
  },
  "functions": {},
  "sortedMiddleware": [
    "/"
  ]
}